hooks/fix_line_endings.py
hooks/generate_init.py
prepper/__init__.py
prepper/__init__.pyi
prepper/_version.py
prepper/caching.py
prepper/enums.py
prepper/exceptions.py
prepper/exportable.py
prepper/io_handlers.py
prepper/py.typed
prepper/utils.py
prepper/tests/__init__.py
prepper/tests/__init__.pyi
prepper/tests/test_IO.py
prepper/tests/test_decorators.py
prepper-1.5.0.dist-info/licenses/LICENSE
prepper-1.5.0.dist-info/METADATA
prepper-1.5.0.dist-info/WHEEL
prepper-1.5.0.dist-info/top_level.txt
prepper-1.5.0.dist-info/RECORD
