Metadata-Version: 2.4
Name: prepper
Version: 1.5.0
Summary: Allows python objects to be stored and loaded from an HDF5 file in a language-agnostic manner
Author-email: Varchas Gopalaswamy <vgop@lle.rochester.edu>
License: MIT
Classifier: Programming Language :: Python :: 3
Requires-Python: >=3.11
License-File: LICENSE
Requires-Dist: numpy
Requires-Dist: h5py>=3.8.0
Requires-Dist: loguru>=0.6.0
Requires-Dist: aenum>=3.1.11
Requires-Dist: pandas>=1.5.1
Requires-Dist: joblib>=1.2.0
Requires-Dist: typing_extensions>=4.6.3
Requires-Dist: lazy_loader
Provides-Extra: ci
Requires-Dist: pytest; extra == "ci"
Requires-Dist: pytest-cov; extra == "ci"
Requires-Dist: hypothesis; extra == "ci"
Requires-Dist: pylint; extra == "ci"
Requires-Dist: xarray; extra == "ci"
Requires-Dist: auto_uncertainties; extra == "ci"
Requires-Dist: periodictable; extra == "ci"
Requires-Dist: arviz; extra == "ci"
Requires-Dist: pint; extra == "ci"
Dynamic: license-file
